astro3D/__init__.py
astro3D/genesis/__init__.py
astro3D/genesis/utils/__init__.py
astro3D/genesis/utils/common.py
astro3D/genesis/utils/convert_indices.py
astro3D/genesis/utils/forest_sorter.py
astro3D/genesis/utils/treefrog_to_lhalo.py
astro3D/genesis/utils/tests/__init__.py
astro3D/genesis/utils/tests/forest_sorter_test.py
astro3D-0.0.0.dev2.dist-info/METADATA
astro3D-0.0.0.dev2.dist-info/RECORD
astro3D-0.0.0.dev2.dist-info/WHEEL
astro3D-0.0.0.dev2.dist-info/top_level.txt
