Metadata-Version: 2.1
Name: astro3D
Version: 0.0.0.dev2
Summary: Python package for Genesis simulations
Home-page: https://github.com/manodeep/astro3D
Author: Manodeep Sinha, Jacob Seiler
Author-email: manodeep@gmail.com
License: MIT
Platform: UNKNOWN
Provides: astro3D
Requires-Python: >=3.5
Requires-Dist: setuptools
Requires-Dist: numpy
Requires-Dist: h5py
